django_forwardemail/__init__.py
django_forwardemail/admin.py
django_forwardemail/apps.py
django_forwardemail/backends.py
django_forwardemail/models.py
django_forwardemail/services.py
django_forwardemail/migrations/0001_initial.py
django_forwardemail/migrations/__init__.py
django_forwardemail-1.0.0.dist-info/licenses/LICENSE
tests/__init__.py
tests/settings.py
tests/test_models.py
tests/urls.py
django_forwardemail-1.0.0.dist-info/METADATA
django_forwardemail-1.0.0.dist-info/WHEEL
django_forwardemail-1.0.0.dist-info/top_level.txt
django_forwardemail-1.0.0.dist-info/RECORD
