Metadata-Version: 2.4
Name: django-forwardemail
Version: 1.0.0
Summary: Django integration for ForwardEmail API with multi-site support
Author: Pacficient Labs
Author-email: PacNPal <pac@pacnp.al>
License-Expression: MIT
Project-URL: Homepage, https://github.com/Pacficient-Labs/django-forwardemail
Project-URL: Documentation, https://django-forwardemail.readthedocs.io/
Project-URL: Repository, https://github.com/Pacficient-Labs/django-forwardemail.git
Project-URL: Bug Tracker, https://github.com/Pacficient-Labs/django-forwardemail/issues
Keywords: django,email,forwardemail,api,multi-site
Classifier: Development Status :: 4 - Beta
Classifier: Environment :: Web Environment
Classifier: Framework :: Django
Classifier: Framework :: Django :: 4.2
Classifier: Framework :: Django :: 5.0
Classifier: Framework :: Django :: 5.1
Classifier: Intended Audience :: Developers
Classifier: Operating System :: OS Independent
Classifier: Programming Language :: Python
Classifier: Programming Language :: Python :: 3
Classifier: Programming Language :: Python :: 3.10
Classifier: Programming Language :: Python :: 3.11
Classifier: Programming Language :: Python :: 3.12
Classifier: Programming Language :: Python :: 3.13
Classifier: Topic :: Communications :: Email
Classifier: Topic :: Internet :: WWW/HTTP
Classifier: Topic :: Software Development :: Libraries :: Python Modules
Requires-Python: >=3.10
License-File: LICENSE
Requires-Dist: Django>=4.2
Requires-Dist: requests>=2.25.0
Provides-Extra: dev
Requires-Dist: pytest>=6.0; extra == "dev"
Requires-Dist: pytest-django>=4.0; extra == "dev"
Requires-Dist: pytest-cov>=2.10; extra == "dev"
Requires-Dist: black>=21.0; extra == "dev"
Requires-Dist: flake8>=3.8; extra == "dev"
Requires-Dist: ruff>=0.1.0; extra == "dev"
Requires-Dist: mypy>=0.800; extra == "dev"
Requires-Dist: django-stubs>=1.7; extra == "dev"
Requires-Dist: factory-boy>=3.2; extra == "dev"
Requires-Dist: twine>=4.0.0; extra == "dev"
Requires-Dist: build>=0.10.0; extra == "dev"
Dynamic: license-file
